ytffmpeg/__init__.py
ytffmpeg/directoryserver.py
ytffmpeg/filter_complex.py
ytffmpeg/genimg.py
ytffmpeg/schema.json
ytffmpeg/types.py
ytffmpeg/cli/__init__.py
ytffmpeg/cli/base.py
ytffmpeg/cli/build.py
ytffmpeg/cli/new.py
ytffmpeg/cli/publish.py
ytffmpeg/cli/refresh.py
ytffmpeg-1.4.0.dist-info/METADATA
ytffmpeg-1.4.0.dist-info/WHEEL
ytffmpeg-1.4.0.dist-info/entry_points.txt
ytffmpeg-1.4.0.dist-info/top_level.txt
ytffmpeg-1.4.0.dist-info/RECORD
