Metadata-Version: 2.4
Name: ytffmpeg
Version: 1.4.0
Summary: Scripts and tools to ease the processing of videos for Social Media platforms.
Author-email: Markizano Draconus <markizano@markizano.net>
Project-URL: Homepage, https://ytffmpeg.markizano.net
Project-URL: Repository, https://github.com/markizano/ytffmpeg
Project-URL: Issues, https://github.com/markizano/ytffmpeg/issues
Requires-Python: >=3.11
Requires-Dist: cherrypy>=18.10.0
Requires-Dist: fabric==3.2.2
Requires-Dist: google-genai>=1.48.0
Requires-Dist: jsonschema==4.24.0
Requires-Dist: kizano==1.0.6
Requires-Dist: langchain[ollama]>=0.3.27
Requires-Dist: numba==0.61.2
Requires-Dist: openai==1.99.9
Requires-Dist: openai-whisper==20250625
Requires-Dist: pillow>=12.0.0
Requires-Dist: python-ffmpeg==2.0.12
Requires-Dist: pyyaml>=6.0.1
Requires-Dist: requests==2.32.4
